.gitignore
LICENSE
README.md
appveyor.yml
setup.py
sesame/__init__.py
sesame/build_shared.py
sesame/build_template_default.py
sesame/build_template_header_only.py
sesame/requirements.txt
sesame/requirements_test.txt
sesame/sesame.py
sesame/commands/__init__.py
sesame/commands/build.py
sesame/commands/dbuild.py
sesame/commands/new.py
sesame/conan_settings/settings.yml
sesame/conan_settings/profiles/sesame-android.profile
sesame/conan_settings/profiles/sesame-base-android-25.profile
sesame/conan_settings/profiles/sesame-base-android-28.profile
sesame/conan_settings/profiles/sesame-base-uwp.profile
sesame/conan_settings/profiles/sesame-base-windows.profile
sesame/templates/gitattributes-template.txt
sesame/templates/gitignore-template.txt
sesame/templates/header-only-build-sesame-template.txt
sesame/templates/header-only-build-template.txt
sesame/templates/header-only-conanfile-template.txt
sesame/templates/license-template.txt
sesame/templates/normal-build-sesame-template.txt
sesame/templates/normal-build-template.txt
sesame/templates/normal-conanfile-template.txt
sesame/templates/test-package-cmakelists-template.txt
sesame/templates/test-package-conanfile-template.txt
sesame/templates/test-package-cpp-template.txt
sesame/templates/tool-build-sesame-template.txt
sesame/templates/tool-build-template.txt
sesame/templates/tool-conanfile-template.txt
sesame/templates/tool-test-package-conanfile-template.txt
sesame_package_tools.egg-info/PKG-INFO
sesame_package_tools.egg-info/SOURCES.txt
sesame_package_tools.egg-info/dependency_links.txt
sesame_package_tools.egg-info/entry_points.txt
sesame_package_tools.egg-info/requires.txt
sesame_package_tools.egg-info/top_level.txt