Metadata-Version: 2.1
Name: sesame-package-tools
Version: 0.4.0
Summary: Sesame Packaging Tools for building Conan recipes
Home-page: https://github.com/birsoyo/sesame-package-tools
Author: Orhun Birsoy
Author-email: orhunbirsoy@gmail.com
License: MIT
Keywords: conan,C/C++,package,libraries,developer,manager,dependency,tool,c,c++,cpp
Platform: UNKNOWN
Classifier: Development Status :: 1 - Planning
Classifier: Intended Audience :: Developers
Classifier: Topic :: Software Development :: Build Tools
Classifier: License :: OSI Approved :: MIT License
Classifier: Programming Language :: Python :: 3.6
Requires-Python: >=3.6
Provides-Extra: test
